<annotation>
  <folder>DATA</folder>
  <filename>366078debdbff8c9_jpg.rf.8ca96ba1b5e5987ae9fe14d4a9d27db9.jpg</filename>
  <source>
    <database>The VOC Database</database>
    <annotation>PASCAL VOC</annotation>
    <image>flickr</image>
  </source>
  <size>
    <width>416</width>
    <height>416</height>
    <depth>3</depth>
  </size>
  <segmented>0</segmented>
  <object>
    <name>Truck</name>
    <pose>Unspecified</pose>
    <truncated>0</truncated>
    <difficult>0</difficult>
    <bndbox>
      <xmin>105</xmin>
      <ymin>240</ymin>
      <xmax>185</xmax>
      <ymax>357</ymax>
    </bndbox>
  </object>
  <object>
    <name>Truck</name>
    <pose>Unspecified</pose>
    <truncated>0</truncated>
    <difficult>0</difficult>
    <bndbox>
      <xmin>257</xmin>
      <ymin>236</ymin>
      <xmax>376</xmax>
      <ymax>364</ymax>
    </bndbox>
  </object>
</annotation>
